{"Columns":[{"ShortTypeName":"ApplicationTypeConfig","strDateType":"applicationtypeconfig","DataType":4,"Name":"applicationTypeConfigs","DisplayName":"applicationTypeConfigs","Nullable":true,"MaxLength":0,"RangeMin":0,"RangeMax":0,"IsVisible":true,"IsNumeric":false,"HasMetaAttribute":false,"MetaAttribute":""},{"ShortTypeName":"Client","strDateType":"client","DataType":4,"Name":"client","DisplayName":"client","Nullable":true,"MaxLength":0,"RangeMin":0,"RangeMax":0,"IsVisible":true,"IsNumeric":false,"HasMetaAttribute":false,"MetaAttribute":""},{"ShortTypeName":"ClientStatusConfig","strDateType":"clientstatusconfig","DataType":4,"Name":"clientStatusConfigs","DisplayName":"clientStatusConfigs","Nullable":true,"MaxLength":0,"RangeMin":0,"RangeMax":0,"IsVisible":true,"IsNumeric":false,"HasMetaAttribute":false,"MetaAttribute":""},{"ShortTypeName":"CountryConfig","strDateType":"countryconfig","DataType":4,"Name":"CountryConfigs","DisplayName":"CountryConfigs","Nullable":true,"MaxLength":0,"RangeMin":0,"RangeMax":0,"IsVisible":true,"IsNumeric":false,"HasMetaAttribute":false,"MetaAttribute":""},{"ShortTypeName":"Stage","strDateType":"stage","DataType":4,"Name":"stage","DisplayName":"stage","Nullable":true,"MaxLength":0,"RangeMin":0,"RangeMax":0,"IsVisible":true,"IsNumeric":false,"HasMetaAttribute":false,"MetaAttribute":""},{"ShortTypeName":"long","strDateType":"long","DataType":5,"Name":"Id","DisplayName":"Id","Nullable":false,"MaxLength":0,"RangeMin":0,"RangeMax":0,"IsVisible":true,"IsNumeric":true,"HasMetaAttribute":false,"MetaAttribute":""},{"ShortTypeName":"string","strDateType":"string","DataType":0,"Name":"email","DisplayName":"email","Nullable":true,"MaxLength":0,"RangeMin":0,"RangeMax":0,"IsVisible":true,"IsNumeric":false,"HasMetaAttribute":false,"MetaAttribute":""}]}